README.md
setup.py
dsmlibrary/__init__.py
dsmlibrary/base.py
dsmlibrary/clickhouse.py
dsmlibrary/datadict.py
dsmlibrary/datanode.py
dsmlibrary/dataset.py
dsmlibrary/mdm.py
dsmlibrary/task.py
dsmlibrary/transfer.py
dsmlibrary.egg-info/PKG-INFO
dsmlibrary.egg-info/SOURCES.txt
dsmlibrary.egg-info/dependency_links.txt
dsmlibrary.egg-info/requires.txt
dsmlibrary.egg-info/top_level.txt
dsmlibrary/utils/__init__.py
dsmlibrary/utils/check.py
dsmlibrary/utils/clickhouse.py
dsmlibrary/utils/dataset.py
dsmlibrary/utils/listDatanode.py
dsmlibrary/utils/requests.py